DaiNiRumenQianduanGongchengFix1/README.md
DaiNiRumenQianduanGongchengFix1/__init__.py
DaiNiRumenQianduanGongchengFix1/__main__.py
DaiNiRumenQianduanGongchengFix1/file.epub
DaiNiRumenQianduanGongchengFix1/index.html
DaiNiRumenQianduanGongchengFix1/css/__init__.py
DaiNiRumenQianduanGongchengFix1/css/annotations.css
DaiNiRumenQianduanGongchengFix1/css/main.css
DaiNiRumenQianduanGongchengFix1/css/normalize.css
DaiNiRumenQianduanGongchengFix1/css/popup.css
DaiNiRumenQianduanGongchengFix1/font/__init__.py
DaiNiRumenQianduanGongchengFix1/font/fontello.eot
DaiNiRumenQianduanGongchengFix1/font/fontello.svg
DaiNiRumenQianduanGongchengFix1/font/fontello.ttf
DaiNiRumenQianduanGongchengFix1/font/fontello.woff
DaiNiRumenQianduanGongchengFix1/img/__init__.py
DaiNiRumenQianduanGongchengFix1/img/annotator-glyph-sprite.png
DaiNiRumenQianduanGongchengFix1/img/annotator-icon-sprite.png
DaiNiRumenQianduanGongchengFix1/img/apple-touch-icon.png
DaiNiRumenQianduanGongchengFix1/img/cancelfullscreen.png
DaiNiRumenQianduanGongchengFix1/img/close.png
DaiNiRumenQianduanGongchengFix1/img/fullscreen.png
DaiNiRumenQianduanGongchengFix1/img/loader.gif
DaiNiRumenQianduanGongchengFix1/img/menu-icon.png
DaiNiRumenQianduanGongchengFix1/img/save.png
DaiNiRumenQianduanGongchengFix1/img/saved.png
DaiNiRumenQianduanGongchengFix1/img/settings-s.png
DaiNiRumenQianduanGongchengFix1/img/settings.png
DaiNiRumenQianduanGongchengFix1/img/star.png
DaiNiRumenQianduanGongchengFix1/js/__init__.py
DaiNiRumenQianduanGongchengFix1/js/epub.js
DaiNiRumenQianduanGongchengFix1/js/epub.min.js
DaiNiRumenQianduanGongchengFix1/js/epub.min.map
DaiNiRumenQianduanGongchengFix1/js/hooks.min.js
DaiNiRumenQianduanGongchengFix1/js/hooks.min.map
DaiNiRumenQianduanGongchengFix1/js/reader.js
DaiNiRumenQianduanGongchengFix1/js/reader.js.map
DaiNiRumenQianduanGongchengFix1/js/reader.min.js
DaiNiRumenQianduanGongchengFix1/js/reader.min.map
DaiNiRumenQianduanGongchengFix1/js/hooks/__init__.py
dai_ni_rumen_qianduan_gongcheng_fix1-2025.3.25.0.dist-info/METADATA
dai_ni_rumen_qianduan_gongcheng_fix1-2025.3.25.0.dist-info/WHEEL
dai_ni_rumen_qianduan_gongcheng_fix1-2025.3.25.0.dist-info/entry_points.txt
dai_ni_rumen_qianduan_gongcheng_fix1-2025.3.25.0.dist-info/top_level.txt
dai_ni_rumen_qianduan_gongcheng_fix1-2025.3.25.0.dist-info/RECORD
